uncertainty_propagation/__init__.py
uncertainty_propagation/directional_simulation/__init__.py
uncertainty_propagation/directional_simulation/integrator.py
uncertainty_propagation/directional_simulation/partitioners.py
uncertainty_propagation/integrator.py
uncertainty_propagation/monte_carlo.py
uncertainty_propagation/most_probable_point.py
uncertainty_propagation/subset_simulation.py
uncertainty_propagation/transform.py
uncertainty_propagation/utils.py
uncertainty_propagation-0.0.2.dist-info/LICENSE
uncertainty_propagation-0.0.2.dist-info/METADATA
uncertainty_propagation-0.0.2.dist-info/WHEEL
uncertainty_propagation-0.0.2.dist-info/RECORD
