Metadata-Version: 2.3
Name: uncertainty-propagation
Version: 0.0.2
Summary: Tools to propagate parameter uncertainty through deterministic black-box functions
License: MIT
Author: Can Bogoclu
Requires-Python: >=3.10,<4.0
Classifier: License :: OSI Approved :: MIT License
Classifier: Programming Language :: Python :: 3
Classifier: Programming Language :: Python :: 3.10
Classifier: Programming Language :: Python :: 3.11
Classifier: Programming Language :: Python :: 3.12
Classifier: Programming Language :: Python :: 3.13
Requires-Dist: experiment-design (>=0.1.4,<0.2.0)
Requires-Dist: joblib (>=1.4.2,<2.0.0)
Requires-Dist: numpy (>=2.1.0,<3.0.0)
Requires-Dist: scipy (>=1.14.1,<2.0.0)
